{
    "dinnerMode": false,
    "announcement": "Welcome to Rumana's Kitchen! Authentic Bengali homemade delicacies prepared fresh from the heart.",
    "items": [
        {
            "available": true,
            "category": "biryani",
            "description": "Traditional Dum Chicken Biriyani of Bengal",
            "diet": "nonveg",
            "hasSizes": true,
            "id": 1,
            "image": "biriyani.jpg",
            "name": "Chicken Biriyani",
            "price": 200,
            "prices": {
                "full": 200,
                "half": 100
            },
            "stockCount": 20
        },
        {
            "available": true,
            "category": "biryani",
            "description": "Authentic Mutton Dum Biriyani of Bengal",
            "diet": "nonveg",
            "hasSizes": true,
            "id": 3,
            "image": "mbiriyani.jpg",
            "name": "Mutton Biriyani",
            "price": 300,
            "prices": {
                "full": 300,
                "half": 150
            },
            "stockCount": 20
        },
        {
            "available": true,
            "category": "curries",
            "description": "5 pieces per plate",
            "diet": "nonveg",
            "id": 5,
            "image": "mutton.jpg",
            "name": "Mutton Kasha",
            "price": 280,
            "stockCount": 20
        },
        {
            "available": true,
            "category": "curries",
            "description": "6 pieces per plate",
            "diet": "nonveg",
            "fallbackImage": "ccurry.jpg",
            "id": 6,
            "image": "ccurry.jpg",
            "name": "Chicken Kasha",
            "price": 180,
            "stockCount": 20
        },
        {
            "available": true,
            "category": "curries",
            "description": "2 pieces per plate",
            "diet": "nonveg",
            "id": 7,
            "image": "fish (1).jpg",
            "name": "Fish Curry",
            "price": 170,
            "stockCount": 20
        },
        {
            "available": true,
            "category": "curries",
            "description": "Per plate",
            "diet": "veg",
            "id": 8,
            "image": "veg.jpg",
            "name": "Mixed Veg Curry",
            "price": 80,
            "stockCount": 20
        },
        {
            "available": true,
            "category": "curries",
            "description": "Per plate",
            "diet": "veg",
            "fallbackImage": "fgovialoo.jpg",
            "id": 9,
            "image": "fgovialoo.jpg",
            "name": "Aloo Gobi Curry",
            "price": 80,
            "stockCount": 20
        },
        {
            "available": true,
            "category": "curries",
            "description": "Per plate",
            "diet": "veg",
            "fallbackImage": "valoo.jpg",
            "id": 10,
            "image": "valoo.jpg",
            "name": "Bhindi Aloo Curry",
            "price": 80,
            "stockCount": 20
        },
        {
            "available": true,
            "category": "curries",
            "description": "Per plate",
            "diet": "veg",
            "fallbackImage": "pgovi.jpg",
            "id": 11,
            "image": "pgovi.jpg",
            "name": "Patta Gobi Curry",
            "price": 80,
            "stockCount": 20
        },
        {
            "available": true,
            "category": "snacks",
            "description": "500 g",
            "diet": "nonveg",
            "fallbackImage": "cpakora.jpg",
            "id": 12,
            "image": "cpakora.jpg",
            "name": "Chicken Pakora (Boneless)",
            "price": 400,
            "stockCount": 20
        },
        {
            "available": true,
            "category": "curries",
            "description": "Per plate",
            "diet": "veg",
            "id": 13,
            "image": "paneer.jpg",
            "name": "Paneer Masala",
            "price": 110,
            "stockCount": 20
        },
        {
            "available": true,
            "category": "curries",
            "description": "Per plate",
            "diet": "veg",
            "id": 14,
            "image": "cpaneer.jpg",
            "name": "Choley Paneer Masala",
            "price": 100,
            "stockCount": 20
        },
        {
            "available": true,
            "category": "sweets",
            "description": "5 pcs",
            "diet": "veg",
            "fallbackImage": "dhokla.jpg",
            "id": 15,
            "image": "dhokla.jpg",
            "name": "Dhokla",
            "price": 50,
            "stockCount": 20
        },
        {
            "available": true,
            "category": "curries",
            "description": "Per plate",
            "diet": "nonveg",
            "id": 16,
            "image": "prawn.png",
            "name": "Prawn Curry",
            "price": 130,
            "stockCount": 20
        },
        {
            "available": true,
            "category": "biryani",
            "description": "Per plate",
            "diet": "veg",
            "fallbackImage": "price.jpg",
            "id": 17,
            "image": "price.jpg",
            "name": "Plain Rice",
            "price": 60,
            "stockCount": 20
        },
        {
            "available": true,
            "category": "snacks",
            "description": "500 g",
            "diet": "veg",
            "fallbackImage": "dalpakora.jpg",
            "id": 18,
            "image": "dalpakora.jpg",
            "name": "Dal Pakora",
            "price": 200,
            "stockCount": 20
        },
        {
            "available": true,
            "category": "snacks",
            "description": "Per piece",
            "diet": "veg",
            "id": 19,
            "image": "nparatha.jpg",
            "name": "Normal Paratha",
            "price": 20,
            "stockCount": 20
        },
        {
            "available": true,
            "category": "snacks",
            "description": "Per piece",
            "diet": "veg",
            "id": 20,
            "image": "paratha.jpg",
            "name": "Laccha Paratha",
            "price": 30,
            "stockCount": 20
        },
        {
            "available": true,
            "category": "sweets",
            "description": "Per plate",
            "diet": "veg",
            "id": 21,
            "image": "gsawaiyan.jpg",
            "name": "Gravy Sawaiyan",
            "price": 70,
            "stockCount": 20
        },
        {
            "available": true,
            "category": "sweets",
            "description": "Per plate",
            "diet": "veg",
            "id": 22,
            "image": "sawaiyan.jpg",
            "name": "Dry Sawaiyan",
            "price": 50,
            "stockCount": 20
        },
        {
            "id": 23,
            "name": "Fried Rice",
            "category": "biryani",
            "diet": "veg",
            "image": "friedrice.jpg",
            "description": "Per plate",
            "price": 120,
            "available": true,
            "stockCount": 20
        }
    ]
}